hydraflow/__init__.py
hydraflow/_py314_compat.py
hydraflow/cli.py
hydraflow/core/__init__.py
hydraflow/core/collection.py
hydraflow/core/context.py
hydraflow/core/group_by.py
hydraflow/core/io.py
hydraflow/core/main.py
hydraflow/core/run.py
hydraflow/core/run_collection.py
hydraflow/core/run_info.py
hydraflow/executor/__init__.py
hydraflow/executor/aio.py
hydraflow/executor/conf.py
hydraflow/executor/io.py
hydraflow/executor/job.py
hydraflow/executor/parser.py
hydraflow/py.typed
hydraflow/utils/__init__.py
hydraflow/utils/progress.py
hydraflow-0.21.3.dist-info/WHEEL
hydraflow-0.21.3.dist-info/entry_points.txt
hydraflow-0.21.3.dist-info/METADATA
hydraflow-0.21.3.dist-info/RECORD
