Metadata-Version: 2.3
Name: hydraflow
Version: 0.21.3
Summary: HydraFlow seamlessly integrates Hydra and MLflow to streamline ML experiment management, combining Hydra's configuration management with MLflow's tracking capabilities.
Keywords: machine-learning,mlflow,hydra,experiment-tracking,mlops,ai,deep-learning,research,data-science
Author: daizutabi
Author-email: daizutabi <daizutabi@gmail.com>
License: MIT License
Classifier: Development Status :: 4 - Beta
Classifier: Environment :: Console
Classifier: Intended Audience :: Developers
Classifier: Intended Audience :: Science/Research
Classifier: License :: OSI Approved :: MIT License
Classifier: Operating System :: OS Independent
Classifier: Programming Language :: Python
Classifier: Programming Language :: Python :: 3.13
Classifier: Programming Language :: Python :: 3.14
Classifier: Topic :: Scientific/Engineering :: Artificial Intelligence
Classifier: Topic :: Software Development :: Libraries :: Python Modules
Requires-Dist: filelock>=3.12.2
Requires-Dist: hydra-core>=1.3
Requires-Dist: joblib>=1.4.0
Requires-Dist: mlflow>=3.6
Requires-Dist: omegaconf>=2.3
Requires-Dist: polars>=1.26
Requires-Dist: python-ulid>=3.0.0
Requires-Dist: rich>=14
Requires-Dist: typer>=0.16
Requires-Python: >=3.13
Project-URL: Documentation, https://daizutabi.github.io/hydraflow/
Project-URL: Issues, https://github.com/daizutabi/hydraflow/issues
Project-URL: Source, https://github.com/daizutabi/hydraflow
